mkreport/__init__.py
mkreport/file_operation.py
mkreport/issue.py
mkreport/mkreport.py
mkreport/print_error.py
mkreport/report_content.txt
mkreport/worked_issues.py
mkreport/worked_time.py
mkreport-1.0.0.dist-info/LICENSE
mkreport-1.0.0.dist-info/METADATA
mkreport-1.0.0.dist-info/WHEEL
mkreport-1.0.0.dist-info/entry_points.txt
mkreport-1.0.0.dist-info/top_level.txt
mkreport-1.0.0.dist-info/RECORD
