Metadata-Version: 2.1
Name: mkreport
Version: 1.0.0
Summary: Make daily report and create time entry at redmine
Home-page: https://github.com/wawawatataru/mkreport
Author: wawawatataru
Author-email: wawawatataru@gmail.com
License: MIT
Platform: UNKNOWN
Requires-Dist: python-redmine
Requires-Dist: pyperclip
Requires-Dist: requests
Requires-Dist: inquirer
